sbx/__init__.py
sbx/__main__.py
sbx/cli/__init__.py
sbx/core/__init__.py
sbx/core/card.py
sbx/core/study.py
sbx/core/utility.py
sbx/service/__init__.py
sbx/service/__main__.py
sbx/ui/__init__.py
sbx/ui/controls.py
sbx/ui/editor.py
sbx/ui/mdlexer.py
sbx/ui/study.py
sbx-0.1.1.dist-info/LICENSE
sbx-0.1.1.dist-info/METADATA
sbx-0.1.1.dist-info/WHEEL
sbx-0.1.1.dist-info/entry_points.txt
sbx-0.1.1.dist-info/top_level.txt
sbx-0.1.1.dist-info/RECORD
