Metadata-Version: 2.1
Name: sbx
Version: 0.1.1
Summary: StudyBox (SBX) - Terminal Flashcards
Home-page: https://github.com/JaDogg/sbx
Author: Bhathiya Perera
Author-email: JaDogg@users.noreply.github.com
License: MIT
Keywords: study flashcard terminal
Platform: UNKNOWN
Classifier: Development Status :: 3 - Alpha
Classifier: Intended Audience :: Information Technology
Classifier: License :: OSI Approved :: MIT License
Classifier: Programming Language :: Python :: 3.6
Classifier: Programming Language :: Python :: 3.7
Classifier: Programming Language :: Python :: 3.8
Requires-Python: >=3.6
Requires-Dist: Pygments (>=2.6.1)
Requires-Dist: prompt-toolkit (>=3.0.5)
Requires-Dist: pytz (>=2020.1)
Requires-Dist: tzlocal (>=2.1)
